[{"personId":"2019RIBE11","personName":"Bárbara Guerra","result":"1442","state":"DF"},{"personId":"2017LEIT01","personName":"Lavynia Marques Leite","result":"1643","state":"DF"},{"personId":"2014MARQ02","personName":"Marlon de V. Marques","result":"1758","state":"DF"},{"personId":"2023LEIT04","personName":"João Victtor Rocha Leite","result":"1810","state":"GO"},{"personId":"2022MART35","personName":"Matheus Oliveira Martins","result":"2201","state":"GO"},{"personId":"2023GODO07","personName":"Miguel Meireles Godoi","result":"2529","state":"DF"},{"personId":"2022MARI13","personName":"Lucas Barbosa Marinho","result":"2599","state":"DF"},{"personId":"2014GOME06","personName":"João Hálisson Sousa Gomes","result":"2704","state":"DF"},{"personId":"2022SOUZ04","personName":"João Marcos Alves Souza","result":"2711","state":"DF"},{"personId":"2016SANT32","personName":"Matheus Ribeiro dos Santos","result":"2897","state":"GO"},{"personId":"2017MACI08","personName":"Luiz Fernando Oliveira Maciel","result":"2975","state":"DF"},{"personId":"2024LONG08","personName":"Matheus Carvalho Longo","result":"3014","state":"GO"},{"personId":"2022CAST14","personName":"Arthur Alves Neiva Castro","result":"3330","state":"DF"},{"personId":"2012SALE02","personName":"Irwin Arruda Sales","result":"3348","state":"GO"},{"personId":"2017SOUZ21","personName":"Érico Lopes de Souza","result":"3454","state":"DF"},{"personId":"2017ALME07","personName":"Gustavo Ruas Sarmento de Almeida","result":"3470","state":"DF"},{"personId":"2012GIOV02","personName":"Luiggi Giovanucci","result":"4035","state":"GO"},{"personId":"2016COST09","personName":"Gabriel Brasileiro Vanderlei Rodrigues da Costa","result":"4060","state":"DF"},{"personId":"2024MOUR12","personName":"Nicolas Kemerich de Moura","result":"4079","state":"GO"},{"personId":"2024FABR01","personName":"João Vitor Fabris","result":"4182","state":"MT"},{"personId":"2019SANT84","personName":"Gabriel Dias Souza dos Santos","result":"4251","state":"DF"},{"personId":"2016FARI04","personName":"Felipe Eduardo Alves de Faria","result":"4682","state":"DF"},{"personId":"2023LEMO07","personName":"Thiago Henrique Silva Lemos","result":"4741","state":"GO"},{"personId":"2024MELO02","personName":"Pedro Almeida de Melo","result":"4862","state":"GO"},{"personId":"2014MORE05","personName":"Pedro Miranda Moreira","result":"5324","state":"DF"},{"personId":"2015SANT33","personName":"Miquéias Dantas dos Santos","result":"5371","state":"DF"},{"personId":"2017SANT59","personName":"Eduardo Freire dos Santos","result":"5405","state":"DF"},{"personId":"2022SILV16","personName":"Péricles Oliveira Silva","result":"5430","state":"DF"},{"personId":"2009KOBA04","personName":"Rodrigo Kenji Asato Kobayashi","result":"5585","state":"MS"},{"personId":"2022FEIT03","personName":"Gabriel Bueno Feitosa","result":"5655","state":"GO"},{"personId":"2017RODR70","personName":"Rafael Vinhal Vaz Rodrigues","result":"5709","state":"DF"},{"personId":"2016BORG04","personName":"Caio Cesar Martins Borges","result":"5786","state":"MT"},{"personId":"2024SANK05","personName":"Kauê Siqueira Santos","result":"5789","state":"DF"},{"personId":"2015LIMA06","personName":"Pedro Gabriel Salviano Augusto Lima","result":"6013","state":"DF"},{"personId":"2010MARQ02","personName":"Arthur Breciani Marques","result":"6664","state":"DF"},{"personId":"2025FERN18","personName":"Rafael Wellington Imafuko Fernandes","result":"6859","state":"DF"},{"personId":"2011GOME02","personName":"Victor Sinan Seixo de Brito Gomes","result":"6883","state":"GO"},{"personId":"2008OLIV01","personName":"Hugo Leonardo de Oliveira Melo","result":"6922","state":"DF"},{"personId":"2019ARAU06","personName":"João Gabriel Guedes Araújo","result":"7651","state":"DF"},{"personId":"2024THIE05","personName":"Nícolas Zimmermann Thiesen","result":"8291","state":"DF"},{"personId":"2015TAKE03","personName":"Gustavo Kenzo Araki Takechi","result":"9883","state":"DF"},{"personId":"2024CUNH02","personName":"Lucas Setúbal Dias da Cunha","result":"9922","state":"DF"},{"personId":"2016SAMA02","personName":"Marcos Paulo dos Santos Sá","result":"10135","state":"DF"},{"personId":"2017NOVA05","personName":"João Luiz Melo Novaes","result":"10679","state":"DF"},{"personId":"2007LAFE01","personName":"Caio José Lafetá","result":"10808","state":"DF"},{"personId":"2010AMOR01","personName":"Christiano de Albuquerque Amorim","result":"11438","state":"GO"},{"personId":"2020SMUL01","personName":"Victor Benevides Smulkowski","result":"11658","state":"GO"},{"personId":"2018MORA03","personName":"Paulo Henrique Matos de Moraes","result":"12587","state":"DF"},{"personId":"2011ALME01","personName":"Diogo Ribeiro de Almeida","result":"13545","state":"GO"},{"personId":"2011LEAN01","personName":"Renato Freire Leandro","result":"17136","state":"GO"}]