[{"personId":"2016ABRE01","personName":"Vitor Wagner Abreu","result":"14386","state":"SC"},{"personId":"2023MEIR02","personName":"Samuel Velho Pereira Meira","result":"14797","state":"SC"},{"personId":"2022ARIN01","personName":"Gustavo Henrique Arins","result":"15759","state":"SC"},{"personId":"2013FORT01","personName":"Christian de Sena Fortunato","result":"16774","state":"SC"},{"personId":"2022MOUR01","personName":"Pedro Contreiras Moura","result":"19032","state":"SC"},{"personId":"2023PERE41","personName":"Pedro Henrique Guerra Pereira","result":"19872","state":"SC"},{"personId":"2023BERT03","personName":"César Octávio Bertoncini","result":"24650","state":"SC"}]