[{"personId":"2019SANT84","personName":"Gabriel Dias Souza dos Santos","result":"564","state":"DF"},{"personId":"2023GODO07","personName":"Miguel Meireles Godoi","result":"685","state":"DF"},{"personId":"2019RIBE11","personName":"Bárbara Guerra","result":"763","state":"DF"},{"personId":"2022SILV16","personName":"Péricles Oliveira Silva","result":"915","state":"DF"},{"personId":"2018SILV72","personName":"Lucas Ferreira Bezerra da Silva","result":"953","state":"DF"},{"personId":"2014MARQ02","personName":"Marlon de V. Marques","result":"1323","state":"DF"},{"personId":"2022SOUS04","personName":"Lucas Dantas de Sousa","result":"1411","state":"DF"},{"personId":"2022MARI13","personName":"Lucas Barbosa Marinho","result":"1499","state":"DF"},{"personId":"2017NOVA05","personName":"João Luiz Melo Novaes","result":"1528","state":"DF"},{"personId":"2014MORE05","personName":"Pedro Miranda Moreira","result":"1823","state":"DF"},{"personId":"2019ARAU06","personName":"João Gabriel Guedes Araújo","result":"2518","state":"DF"},{"personId":"2018MORA03","personName":"Paulo Henrique Matos de Moraes","result":"5664","state":"DF"}]