[{"personId":"2017CAVA05","personName":"Thomaz Silva Cavalcanti","result":"1750","state":"RN"},{"personId":"2016REBO01","personName":"Victor Medeiros Rebouças","result":"2025","state":"RN"},{"personId":"2013SILV12","personName":"Pablo Eduardo Nikolais Teixeira Bonifácio da Silva","result":"2081","state":"RN"},{"personId":"2018MONA03","personName":"Walterklayson dos Santos Monastirski","result":"2453","state":"RN"},{"personId":"2017SOUS06","personName":"Thalison Roberto Ferreira de Sousa","result":"3394","state":"RN"}]