[{"personId":"2016SATO01","personName":"Caio Hideaki Sato","result":"3506","state":"SP"},{"personId":"2019DIAS02","personName":"Mario Armando Takahashi Martins Dias","result":"3925","state":"SP"},{"personId":"2015CECC01","personName":"Vicenzo Guerino Cecchini","result":"4084","state":"SP"},{"personId":"2015MATT05","personName":"Enzo Mattos","result":"4256","state":"SP"},{"personId":"2014YUNO01","personName":"Lucas Ichiro Yunomae","result":"4371","state":"SP"},{"personId":"2019FUJI09","personName":"Tiago Akihiro Fujita","result":"4601","state":"SP"},{"personId":"2023NACI01","personName":"Isabela da Ponte Nacif","result":"4860","state":"SP"},{"personId":"2022SASA03","personName":"Pedro Paulo Lima Sasaki","result":"4942","state":"SP"},{"personId":"2018GOME29","personName":"Frederico Canal Gomes","result":"5317","state":"SP"},{"personId":"2013OLIV01","personName":"Fabiano Pinheiro de Oliveira","result":"5690","state":"SP"},{"personId":"2016CARD06","personName":"Felipe Cardim","result":"5751","state":"SP"},{"personId":"2022CLEM05","personName":"Samuel Bortolan Clemente","result":"5837","state":"SP"},{"personId":"2022BERN01","personName":"Beatriz Hernandes Bernardes","result":"5973","state":"SP"},{"personId":"2016TANN01","personName":"Ana Beatriz M. Tannenbaum","result":"6208","state":"SP"},{"personId":"2018LIMA24","personName":"Caique Crispim de Lima","result":"6550","state":"SP"},{"personId":"2015VERA02","personName":"Diego Boasso Vera","result":"7525","state":"SP"},{"personId":"2016LIPS01","personName":"Adriano Matoba Lipski","result":"7860","state":"SP"},{"personId":"2016FIOR01","personName":"Giovane Rubin Fioravanti","result":"8700","state":"SP"},{"personId":"2018SELL01","personName":"Carlos Augusto Gianesi Seller","result":"9389","state":"SP"},{"personId":"2015CARV06","personName":"Iuri Grangeiro Carvalho","result":"11128","state":"SP"},{"personId":"2022EGGJ01","personName":"João Henrique Andrade Egg","result":"12402","state":"SP"},{"personId":"2023DUAR03","personName":"Renato Coelho Mathias Duarte","result":"17773","state":"SP"},{"personId":"2022PINE01","personName":"Rodrigo Perez Oliveira Pineda","result":"18778","state":"SP"},{"personId":"2015SANT16","personName":"Andrei dos Santos","result":"28310","state":"SP"}]