[{"personId":"2016SANT66","personName":"João Vinícius Santos","result":"156","state":"BA"},{"personId":"2016COEL04","personName":"Suzane Coelho","result":"256","state":"BA"},{"personId":"2017BORG02","personName":"Gabriel Bergue","result":"276","state":"BA"},{"personId":"2019COST15","personName":"Lucas Nepomuceno Costa","result":"356","state":"BA"},{"personId":"2023VITO03","personName":"Ryan Daniel Vianna Vitória","result":"372","state":"BA"},{"personId":"2019SOUT01","personName":"Lucas de Lima Souto","result":"387","state":"BA"},{"personId":"2011LIMA02","personName":"Bruno Fonsêca Coelho Lima","result":"395","state":"BA"},{"personId":"2022CAST33","personName":"Pedro Vitor Sant Anna Castro","result":"413","state":"BA"},{"personId":"2016SILV02","personName":"Luiz Fellipe Oliuza Leal Silva","result":"447","state":"BA"},{"personId":"2017BARR24","personName":"Luan Ferreira","result":"465","state":"BA"},{"personId":"2016SILV72","personName":"Ícaro Pereira Silva","result":"467","state":"BA"},{"personId":"2023FILH01","personName":"Marcelo Teixeira Reis Filho","result":"481","state":"BA"},{"personId":"2022CARV03","personName":"Rafael Silva Carvalho","result":"492","state":"BA"},{"personId":"2023JESU06","personName":"Matheus Morais de Jesus","result":"492","state":"BA"},{"personId":"2018OLIV28","personName":"Kalani Oliveira","result":"525","state":"BA"},{"personId":"2022BRIT07","personName":"Renata Ferrer Brito","result":"564","state":"BA"},{"personId":"2011LIMA03","personName":"Henrique Fonsêca Coelho Lima","result":"570","state":"BA"},{"personId":"2017NUNE09","personName":"Lucca Miranda Nunes","result":"592","state":"BA"},{"personId":"2018CANE01","personName":"Víctor Lucas Rosada Canesin","result":"602","state":"BA"},{"personId":"2023PASS04","personName":"Caetano Passos","result":"617","state":"BA"},{"personId":"2019CASS06","personName":"Arthur Aguiar Cassimiro","result":"621","state":"BA"},{"personId":"2022TEIX01","personName":"João Teixeira e Teixeira","result":"635","state":"BA"},{"personId":"2023DONE03","personName":"Tobias Doneff","result":"638","state":"BA"},{"personId":"2017DIAS05","personName":"Camila Souza Dias","result":"640","state":"BA"},{"personId":"2020AMAR01","personName":"Pedro Lucas Cordeiro Amaral","result":"642","state":"BA"},{"personId":"2022SILV65","personName":"Emanuel Evangelista Silva","result":"651","state":"BA"},{"personId":"2024BARB26","personName":"Leonardo Fabiano","result":"702","state":"BA"},{"personId":"2023MORE13","personName":"Caio Lucas Vieira Moreno","result":"709","state":"BA"},{"personId":"2024ARAU04","personName":"Ruan Pablo Assis de Araújo","result":"719","state":"BA"},{"personId":"2023CONC01","personName":"Mel Jesus Conceiçao","result":"759","state":"BA"},{"personId":"2023COST22","personName":"Bruna Oliveira Sousa Costa","result":"787","state":"BA"},{"personId":"2022SILV59","personName":"Ismael dos Santos Corrêa da Silva","result":"796","state":"BA"},{"personId":"2022PERE60","personName":"Flavia Silva Pereira","result":"829","state":"BA"},{"personId":"2023JESU09","personName":"Nykolas Nascimento Jesus","result":"846","state":"BA"},{"personId":"2024DAVI08","personName":"Rafael da Silva David","result":"855","state":"BA"},{"personId":"2023CARV13","personName":"Victor Gabriel Bevenuta de Carvalho","result":"860","state":"BA"},{"personId":"2025FREI01","personName":"Júlia Cunha Freitas","result":"860","state":"BA"},{"personId":"2018MEND23","personName":"Sérgio Hernandes Piancó Mendes","result":"875","state":"BA"},{"personId":"2016SANT03","personName":"Andrey Conceição","result":"889","state":"BA"},{"personId":"2017FILH02","personName":"Walter Mota Quintela Filho","result":"912","state":"BA"},{"personId":"2023MICU01","personName":"Miguel Andrade Micucci","result":"995","state":"BA"},{"personId":"2023SOUZ21","personName":"Kauan Macedo de Souza","result":"1022","state":"BA"},{"personId":"2019OLIV37","personName":"Márcio Victor Rodrigues de Oliveira","result":"1031","state":"BA"},{"personId":"2023SANL01","personName":"Luís Henrique Ramos dos Santos","result":"1061","state":"BA"},{"personId":"2024JUNI01","personName":"André de Oliveira Silva Ferreira Júnior","result":"1077","state":"BA"},{"personId":"2023SACR01","personName":"Guilherme Cardoso Sacramento","result":"1106","state":"BA"},{"personId":"2022OLIV09","personName":"Arthur Calheira","result":"1133","state":"BA"},{"personId":"2023CAMP29","personName":"Carlos Vinícius de Almeida Freitas Campos","result":"1135","state":"BA"},{"personId":"2025ALVE01","personName":"Mathias Bittencourt de Azevedo Alves","result":"1149","state":"BA"},{"personId":"2019LUZM01","personName":"Mateus Padilha Luz","result":"1165","state":"BA"},{"personId":"2023FREI12","personName":"Levi Pamponet Freixo","result":"1172","state":"BA"},{"personId":"2016SANT06","personName":"Janaina de Santana Santos","result":"1222","state":"BA"},{"personId":"2016DANI01","personName":"Lucas Daniel","result":"1242","state":"BA"},{"personId":"2022SILV60","personName":"Saulo Rezende Campos Nunes da Silva","result":"1251","state":"BA"},{"personId":"2018CARV01","personName":"Rafael Lélis de Carvalho","result":"1291","state":"BA"},{"personId":"2023SILV14","personName":"Sofia Guimarães Vieira Silva","result":"1293","state":"BA"},{"personId":"2015MARB01","personName":"Marjorie Nunes","result":"1304","state":"BA"},{"personId":"2016NASC01","personName":"Osanyo Victor de Jesus Nascimento","result":"1326","state":"BA"},{"personId":"2024CAIR02","personName":"Bernardo Boaventura Caires","result":"1400","state":"BA"},{"personId":"2017NETO01","personName":"João Felix Barreto Neto","result":"1421","state":"BA"},{"personId":"2022SILV66","personName":"Raphael Cerqueira da Silva","result":"1425","state":"BA"},{"personId":"2022GUIM02","personName":"João Vítor de Souza Guimarães","result":"1458","state":"BA"},{"personId":"2018RODR51","personName":"Gustavo Bacelar Barreoros Rodrigues","result":"1612","state":"BA"},{"personId":"2019MORE02","personName":"Mirian Vitória Moretti","result":"1632","state":"BA"},{"personId":"2017BRAS02","personName":"Daniel de Oliveira Brasileiro","result":"1637","state":"BA"},{"personId":"2018WUBI02","personName":"Bia Wu","result":"1673","state":"BA"},{"personId":"2024ABRE03","personName":"Henrique Xavier Abreu","result":"1750","state":"BA"},{"personId":"2025SILV44","personName":"Bernardo Araújo Silva","result":"1755","state":"BA"},{"personId":"2017GOME32","personName":"Mateus Lins Gomes","result":"1862","state":"BA"},{"personId":"2023SOUZ20","personName":"Joaquim Macedo Chastinet de Souza","result":"1982","state":"BA"},{"personId":"2016SANT07","personName":"Rafael Correia de Santana","result":"2042","state":"BA"},{"personId":"2024MOUR09","personName":"João Marcelo Francisco Moura","result":"2061","state":"BA"},{"personId":"2022SANT47","personName":"Miguel Ferraz Curi de Santana","result":"2154","state":"BA"},{"personId":"2025LIMA22","personName":"Íris Bulcão Lima","result":"2373","state":"BA"},{"personId":"2024RODP01","personName":"Paco Lá Pher Si Rodrigues","result":"2600","state":"BA"},{"personId":"2016HOLT01","personName":"Heron Negreiros Holtz","result":"2886","state":"BA"},{"personId":"2019ANDR38","personName":"Camila Cruzes de Andrade","result":"2941","state":"BA"},{"personId":"2016VIAN01","personName":"Kim Vianna","result":"2954","state":"BA"},{"personId":"2019PERE01","personName":"Aziel Luz Pereira","result":"3326","state":"BA"},{"personId":"2016SILV73","personName":"Rebeca Cristina Miranda da Silva","result":"3394","state":"BA"},{"personId":"2016MORA38","personName":"Tiago Sousa Moraes","result":"3621","state":"BA"}]