[{"personId":"2016SATO01","personName":"Caio Hideaki Sato","result":"4675","state":"SP"},{"personId":"2018GOME29","personName":"Frederico Canal Gomes","result":"5182","state":"SP"},{"personId":"2015CECC01","personName":"Vicenzo Guerino Cecchini","result":"5355","state":"SP"},{"personId":"2022SASA03","personName":"Pedro Paulo Lima Sasaki","result":"5416","state":"SP"},{"personId":"2019FUJI09","personName":"Tiago Akihiro Fujita","result":"5427","state":"SP"},{"personId":"2014YUNO01","personName":"Lucas Ichiro Yunomae","result":"5565","state":"SP"},{"personId":"2016TANN01","personName":"Ana Beatriz M. Tannenbaum","result":"5859","state":"SP"},{"personId":"2012ROQU01","personName":"Pedro Roque","result":"6186","state":"MG"},{"personId":"2015CAMP01","personName":"Rafael Carreiro Campos","result":"6287","state":"MG"},{"personId":"2016LIPS01","personName":"Adriano Matoba Lipski","result":"6331","state":"SP"},{"personId":"2018LIMA24","personName":"Caique Crispim de Lima","result":"6362","state":"SP"},{"personId":"2015MATT05","personName":"Enzo Mattos","result":"6421","state":"SP"},{"personId":"2016FIOR01","personName":"Giovane Rubin Fioravanti","result":"6425","state":"SP"},{"personId":"2022CLEM05","personName":"Samuel Bortolan Clemente","result":"6830","state":"SP"},{"personId":"2022HANT01","personName":"Thiago Han","result":"6863","state":"SP"},{"personId":"2018DULL02","personName":"Gustavo Dias Dullens","result":"6959","state":"RJ"},{"personId":"2013MOTT01","personName":"Enzo Gonçalves Motta","result":"6968","state":"SP"},{"personId":"2021SHAW02","personName":"Vinicius Shaw","result":"7026","state":"SP"},{"personId":"2015FIGU02","personName":"Marcus Figueiredo","result":"7078","state":"MG"},{"personId":"2015VERA02","personName":"Diego Boasso Vera","result":"7117","state":"SP"},{"personId":"2016CARD06","personName":"Felipe Cardim","result":"7146","state":"SP"},{"personId":"2015BELO02","personName":"Pedro Henrique Maciel Ceccopieri Belo","result":"7236","state":"RJ"},{"personId":"2022BERN01","personName":"Beatriz Hernandes Bernardes","result":"7340","state":"SP"},{"personId":"2017SOUZ10","personName":"Gabriel Lincon Souza","result":"7446","state":"MG"},{"personId":"2014MELL03","personName":"Gabriel Sargeiro Gomes de Mello","result":"7463","state":"RJ"},{"personId":"2022NEVE01","personName":"Kaique de Oliveira Neves","result":"7467","state":"RJ"},{"personId":"2024SANT39","personName":"Gabriel Vasconcellos Zavrisko dos Santos","result":"7497","state":"SP"},{"personId":"2019COZE01","personName":"Maysa Santos Cozer","result":"7543","state":"ES"},{"personId":"2018MEDE01","personName":"Victor Rampinelli Villar de Medeiros","result":"7623","state":"RJ"},{"personId":"2023ANDR19","personName":"Kauã dos Santos Andrade","result":"7634","state":"SP"},{"personId":"2012MAIA01","personName":"João Guilherme Barejan Maiale","result":"7662","state":"SP"},{"personId":"2023FREI04","personName":"Arthur Braum Coelho Freitas","result":"7824","state":"ES"},{"personId":"2022DASH05","personName":"Dillinger Dashiell","result":"7875","state":"SP"},{"personId":"2024COST25","personName":"Vitor Dantas da Costa","result":"7934","state":"SP"},{"personId":"2019DIAS02","personName":"Mario Armando Takahashi Martins Dias","result":"7946","state":"SP"},{"personId":"2013OLIV03","personName":"Mauricio Pinheiro de Oliveira","result":"7954","state":"SP"},{"personId":"2014REZE02","personName":"Matheus de Souza Rezende","result":"8013","state":"MG"},{"personId":"2015SILV62","personName":"Pedro Victor Ferreira Silva","result":"8045","state":"MG"},{"personId":"2019PINH01","personName":"Edgar Nogueira Garcia Pinho","result":"8080","state":"RJ"},{"personId":"2017REZE01","personName":"Vitória Santana Rezende","result":"8085","state":"MG"},{"personId":"2019SILV06","personName":"Gustavo Fonseca da Silva","result":"8121","state":"SP"},{"personId":"2015RODO01","personName":"Mateus Garcia Rodolfo","result":"8165","state":"SP"},{"personId":"2009BARB01","personName":"Gabriel Dechichi Barbar","result":"8185","state":"MG"},{"personId":"2023NEVE01","personName":"Rafael Hiroshi Eguchi Neves","result":"8339","state":"ES"},{"personId":"2013ITOW01","personName":"William Yudi Matunoshita Ito","result":"8354","state":"SP"},{"personId":"2019MIYA05","personName":"Pedro Lobeto Miyamoto","result":"8464","state":"SP"},{"personId":"2017TESC01","personName":"Pedro Henrique Tesch","result":"8493","state":"RJ"},{"personId":"2014SANT31","personName":"Bernardo Zakur Corrêa Santos","result":"8748","state":"SP"},{"personId":"2015FAGU01","personName":"Samuel Asafe Ludugel Fagundes","result":"8751","state":"ES"},{"personId":"2015AMER01","personName":"Gabriel Valenciano Américo","result":"8918","state":"SP"},{"personId":"2022EGGJ01","personName":"João Henrique Andrade Egg","result":"8948","state":"SP"},{"personId":"2013OLIV01","personName":"Fabiano Pinheiro de Oliveira","result":"8953","state":"SP"},{"personId":"2015CARV06","personName":"Iuri Grangeiro Carvalho","result":"8965","state":"SP"},{"personId":"2023QUIN18","personName":"Daniel Lencastre de Souza Quintão","result":"8994","state":"RJ"},{"personId":"2017SEMO02","personName":"Marcos Ferreira Semolini","result":"9307","state":"SP"},{"personId":"2024SANT15","personName":"Mariane Martins dos Santos","result":"9492","state":"MG"},{"personId":"2024MIZU03","personName":"Diego Eiji Akatsuka Mizuta","result":"9521","state":"MG"},{"personId":"2022FERN29","personName":"Pedro Lima Fernandes","result":"9575","state":"SP"},{"personId":"2017MEDE01","personName":"Ricardo Magno Santos Medeiros","result":"9633","state":"MG"},{"personId":"2023NACI01","personName":"Isabela da Ponte Nacif","result":"9745","state":"SP"},{"personId":"2010TERU01","personName":"Alexandre Key Wakate Teruya","result":"9750","state":"SP"},{"personId":"2022PINE01","personName":"Rodrigo Perez Oliveira Pineda","result":"9755","state":"SP"},{"personId":"2016OLIV01","personName":"Yuri de Oliveira","result":"9780","state":"ES"},{"personId":"2018SILV28","personName":"Pedro Henrique de Jesus Silva","result":"9795","state":"ES"},{"personId":"2018CARR06","personName":"Leonardo José Carrari","result":"9810","state":"MG"},{"personId":"2019VIEI03","personName":"Eduardo de Carvalho Vieira","result":"9971","state":"MG"},{"personId":"2024RIOS12","personName":"Gabriel Assis Rios","result":"10075","state":"MG"},{"personId":"2015OLIV20","personName":"Henrique Luiz Souza de Oliveira","result":"10116","state":"SP"},{"personId":"2014OLIV05","personName":"Matheus Silva Carvalho de Oliveira","result":"10157","state":"RJ"},{"personId":"2011SOBR01","personName":"Alrimar Dias Rocha Sobrinho","result":"10179","state":"SP"},{"personId":"2017ANDR14","personName":"Jônatas Tavares Andrade","result":"10183","state":"RJ"},{"personId":"2016GUSM02","personName":"Vitor Prando Gusmão","result":"10352","state":"ES"},{"personId":"2023ALEX14","personName":"Sofia Pirovani Alexandre","result":"10357","state":"RJ"},{"personId":"2013NAKA01","personName":"Fabio Nakamura","result":"10422","state":"SP"},{"personId":"2023RETT03","personName":"Elias Retti","result":"10516","state":"SP"},{"personId":"2024FEIT02","personName":"Leonardo Carvalho Feitosa","result":"10686","state":"SP"},{"personId":"2022LIMA01","personName":"Maria Clara Rodrigues Garola Lima","result":"10795","state":"SP"},{"personId":"2017NANT01","personName":"Erik Lucas Santos Nantes","result":"10949","state":"MG"},{"personId":"2024SILV57","personName":"Daniel Rici da Silva","result":"11053","state":"SP"},{"personId":"2009DINI01","personName":"Felipe de Carvalho Diniz","result":"11057","state":"RJ"},{"personId":"2012PINT01","personName":"Jorge Augusto Siqueira Pinto","result":"11069","state":"SP"},{"personId":"2015SANT16","personName":"Andrei dos Santos","result":"11170","state":"SP"},{"personId":"2022CORR02","personName":"Igor Amaral Correa","result":"11212","state":"SP"},{"personId":"2012CAMP03","personName":"Gabriel Pereira Campanha","result":"11234","state":"SP"},{"personId":"2013ESTE02","personName":"Augusto Rosa Esteves","result":"11257","state":"SP"},{"personId":"2013RENN01","personName":"Tarik Rennan Assef Ayoub","result":"11286","state":"SP"},{"personId":"2014MONT03","personName":"Gustavo Ribeiro Monteiro","result":"11325","state":"RJ"},{"personId":"2014ONOD01","personName":"Yngwie Onodera","result":"11348","state":"SP"},{"personId":"2007GUIM01","personName":"Pedro Santos Guimarães","result":"11368","state":"MG"},{"personId":"2024SILV23","personName":"Júlio Batista Tomáz da Silva","result":"11417","state":"RJ"},{"personId":"2024VASS01","personName":"Daniel Arruda Vasseur","result":"11425","state":"MG"},{"personId":"2014KUDO01","personName":"Daniel Junji Kudo","result":"11464","state":"SP"},{"personId":"2019CASS04","personName":"Nicolas D. Cassemiro","result":"11497","state":"SP"},{"personId":"2016SILV19","personName":"Flávio Henrique Andrade Lemos da Silva","result":"11499","state":"SP"},{"personId":"2017RODR20","personName":"Augusto Ferreira Rodrigues","result":"11510","state":"SP"},{"personId":"2015SATO01","personName":"Lucas Akio Fujita Sato","result":"11618","state":"SP"},{"personId":"2023JOAO01","personName":"Felipe Teodoro São João","result":"11687","state":"SP"},{"personId":"2023COST11","personName":"Gabriel Rodrigues Costa","result":"11762","state":"SP"},{"personId":"2011LIMA01","personName":"Allyson Dias de Lima","result":"11854","state":"SP"},{"personId":"2018UEHA01","personName":"Victor Jun Teruya Uehara","result":"11893","state":"SP"},{"personId":"2022SANT05","personName":"Emanuel Victor Araújo dos Santos","result":"11899","state":"RJ"},{"personId":"2023SOAR01","personName":"Isaac Rafael Oliveira Soares","result":"11901","state":"ES"},{"personId":"2022GONC01","personName":"Mariana Castro","result":"11999","state":"RJ"},{"personId":"2015GARC16","personName":"Antonio Miguel Leutwiler Garcia","result":"12069","state":"SP"},{"personId":"2024MORA61","personName":"André Fazito Morais","result":"12076","state":"MG"},{"personId":"2022CARV10","personName":"Bruno Murillo de Oliveira Carvalho","result":"12088","state":"SP"},{"personId":"2023SANT65","personName":"Miguel de Oliveira Dias dos Santos","result":"12099","state":"RJ"},{"personId":"2019PAIV01","personName":"Felipe Hatanaka Martins Paiva","result":"12117","state":"SP"},{"personId":"2015KAVA01","personName":"Mathias Kavai","result":"12209","state":"SP"},{"personId":"2019BARR06","personName":"Bruno Vivaldi Barrella","result":"12223","state":"SP"},{"personId":"2015PAES01","personName":"João Vitor Almeida Paes","result":"12273","state":"RJ"},{"personId":"2019SOUZ21","personName":"Igor Pereira de Souza","result":"12297","state":"SP"},{"personId":"2011GOTT03","personName":"Josué Dell'Orto Gottardi","result":"12332","state":"ES"},{"personId":"2014LEHW01","personName":"Daniel Lehwing","result":"12339","state":"SP"},{"personId":"2013VIDA01","personName":"Tiago Oliveira Vidal","result":"12432","state":"SP"},{"personId":"2014LAND06","personName":"Guilherme Henrique Paes Landim","result":"12434","state":"SP"},{"personId":"2017SANT34","personName":"Marlom Messias dos Santos","result":"12515","state":"SP"},{"personId":"2018NASC19","personName":"Breno Gustavo da Silva Nascimento","result":"12653","state":"SP"},{"personId":"2014BATI04","personName":"Anderson Ferreira Batista","result":"12709","state":"SP"},{"personId":"2025SANT34","personName":"Samir Oliveira Ramos dos Santos","result":"12725","state":"MG"},{"personId":"2011MELO01","personName":"Leonardo Caetano Araújo de Melo","result":"12771","state":"SP"},{"personId":"2024FELI11","personName":"Gabriel Pereira Felipe","result":"12850","state":"MG"},{"personId":"2017PIRE01","personName":"Pedro Luiz Ferreira Pires","result":"12855","state":"SP"},{"personId":"2016AZEV03","personName":"Carlos Gabriel de Azevedo","result":"12886","state":"ES"},{"personId":"2025FILH08","personName":"Roney Sterza Marczak Filho","result":"13141","state":"SP"},{"personId":"2011CUNH01","personName":"André Lars da Cunha","result":"13192","state":"SP"},{"personId":"2012MENG02","personName":"Daniel Maggioni Meng","result":"13196","state":"SP"},{"personId":"2016GODO01","personName":"Rodrigo de Castro Godoy","result":"13214","state":"ES"},{"personId":"2024SOUS10","personName":"Luiz Fernando Santos de Sousa","result":"13305","state":"SP"},{"personId":"2015CARN03","personName":"Felipe Gomes Carneiro","result":"13335","state":"SP"},{"personId":"2019SANT64","personName":"Gustavo Dutra Santolin","result":"13336","state":"ES"},{"personId":"2010GRAC02","personName":"Fabio Bini Graciose","result":"13372","state":"SP"},{"personId":"2013SOUZ01","personName":"José Artur Cunha de Souza","result":"13432","state":"SP"},{"personId":"2017SANT12","personName":"Renan da Cunha Santos","result":"13453","state":"SP"},{"personId":"2018COST11","personName":"Maurício Amaral da Costa","result":"13458","state":"MG"},{"personId":"2014MOUR01","personName":"Beatriz de Araujo Mourão","result":"13543","state":"SP"},{"personId":"2016GONC02","personName":"Henrique Coelho","result":"13630","state":"RJ"},{"personId":"2012MEDE01","personName":"Lucas Cardoso Medeiros","result":"13726","state":"SP"},{"personId":"2014SANT33","personName":"Vinicius Raphael Maximo dos Santos","result":"13732","state":"SP"},{"personId":"2015PINH04","personName":"Gabriel Pinheiro","result":"13769","state":"SP"},{"personId":"2009NAKA02","personName":"Luiz Alberto Eiti Nakamura","result":"13783","state":"RJ"},{"personId":"2013SABI01","personName":"Gabriel Luiz Pires Sabino","result":"13829","state":"SP"},{"personId":"2022FIGU05","personName":"Pedro Soares Figueiredo","result":"14063","state":"RJ"},{"personId":"2017LISB01","personName":"Felipe Dutra Lisboa","result":"14073","state":"SP"},{"personId":"2017CRUZ27","personName":"Leonardo Paixão Cruz","result":"14123","state":"SP"},{"personId":"2015FREI01","personName":"Igor Butter Leão de Freitas","result":"14156","state":"RJ"},{"personId":"2014SANT26","personName":"Pedro Silva Bueno dos Santos","result":"14229","state":"SP"},{"personId":"2015KITA02","personName":"Henrique Yudi Kitamura","result":"14229","state":"SP"},{"personId":"2013SOUS01","personName":"Gustavo Silva Sousa","result":"14309","state":"SP"},{"personId":"2014CRUZ04","personName":"Hércules Felipe Ramos Da Cruz","result":"14327","state":"RJ"},{"personId":"2023AMAR10","personName":"Samuel Katsuo Yamamoto Amaral","result":"14369","state":"RJ"},{"personId":"2015BATA01","personName":"Guilherme Eduardo Silva Batalhoti","result":"14408","state":"SP"},{"personId":"2023PACH07","personName":"João Vitor Siqueira Pacheco","result":"14426","state":"RJ"},{"personId":"2024TAVA01","personName":"Benjamin Ferreira Tavares","result":"14557","state":"RJ"},{"personId":"2015GASP01","personName":"Caio Barbosa Gaspar","result":"14663","state":"SP"},{"personId":"2017VIEI04","personName":"Samuel Castro Vieira","result":"14815","state":"MG"},{"personId":"2016BART08","personName":"Gabriel Henrique Cabral Barthasson","result":"14824","state":"MG"},{"personId":"2012PARA03","personName":"Renan Eduardo Parazzi","result":"14845","state":"SP"},{"personId":"2018FERR07","personName":"Arthur Gimenes Alvarenga Ferrari","result":"14873","state":"ES"},{"personId":"2017VIAN01","personName":"Matheus Casassa","result":"14969","state":"SP"},{"personId":"2012MART02","personName":"Victor Hugo Brino Martins","result":"15004","state":"SP"},{"personId":"2010REIS01","personName":"Tenyson Couto dos Reis","result":"15012","state":"ES"},{"personId":"2016JORG02","personName":"Yan Espindola da Costa Jorge","result":"15150","state":"SP"},{"personId":"2007CINO01","personName":"Rafael de Andrade Cinoto","result":"15284","state":"SP"},{"personId":"2015NETO01","personName":"João Sérgio da Silva Neto","result":"15343","state":"SP"},{"personId":"2022BOCC01","personName":"Marco Termini Boccardo","result":"15349","state":"SP"},{"personId":"2015SANT08","personName":"Sávio Gabriel Ferreira dos Santos","result":"15533","state":"SP"},{"personId":"2012SILV07","personName":"Marcos Vinícius Vieira Takahashi da Silva","result":"15605","state":"SP"},{"personId":"2025BRAN14","personName":"Lucas Mathias dos Anjos Brand","result":"15625","state":"SP"},{"personId":"2017CALD04","personName":"Roberto Caldas","result":"15697","state":"RJ"},{"personId":"2013SILV01","personName":"Rubix Azevedo Martins da Silva","result":"15914","state":"SP"},{"personId":"2018SILV30","personName":"Everaldo Leandro Baracho da Silva","result":"16008","state":"RJ"},{"personId":"2023PAUL09","personName":"Arthur Khachaturyan de Paula","result":"16047","state":"SP"},{"personId":"2023LIZA04","personName":"Davi Machado Lizarbe","result":"16113","state":"RJ"},{"personId":"2012MENG03","personName":"Lucas Henrique Meng","result":"16276","state":"SP"},{"personId":"2024SERP01","personName":"Rykelmy Fernandes Serpa","result":"16299","state":"ES"},{"personId":"2013FERR04","personName":"Guilherme Ferreira","result":"16446","state":"SP"},{"personId":"2017PERE58","personName":"Vitor Samuel Pereira","result":"16516","state":"MG"},{"personId":"2017GOME14","personName":"Eliseu Gomes","result":"16554","state":"SP"},{"personId":"2023SANT21","personName":"Arthur Corrêa Lube Santos","result":"16714","state":"ES"},{"personId":"2022SILV07","personName":"Otavio José Silveira","result":"16742","state":"SP"},{"personId":"2012ANDR01","personName":"Daniel Adrian López de Andrade","result":"16763","state":"SP"},{"personId":"2022ALVE07","personName":"Victor Farles Cavalcante Alves","result":"16786","state":"ES"},{"personId":"2024OLIV50","personName":"Lucas Santos de Oliveira","result":"17000","state":"SP"},{"personId":"2019CAMP10","personName":"Guilherme Santana Campos","result":"17047","state":"SP"},{"personId":"2023LIMA26","personName":"Henrique Pereira Souza Lima","result":"17101","state":"SP"},{"personId":"2017WEST04","personName":"Nicolas Perez","result":"17102","state":"MG"},{"personId":"2017CAMA16","personName":"André Silva Camargo","result":"17267","state":"MG"},{"personId":"2016FILG01","personName":"Felipe Ferreira Neto Filgueiras","result":"17378","state":"RJ"},{"personId":"2013GOYA01","personName":"Henry Hideki Goya","result":"17428","state":"SP"},{"personId":"2014SILV02","personName":"Giulia Chiucchi Silva","result":"17453","state":"SP"},{"personId":"2024SILV48","personName":"Christian Santos da Silva","result":"17501","state":"ES"},{"personId":"2017CASA05","personName":"João Francisco Stolle Paixão e Casarões","result":"17516","state":"MG"},{"personId":"2017BARB06","personName":"Pedro Paulo dos Santos Barbosa","result":"17595","state":"RJ"},{"personId":"2014BALB01","personName":"Gabriel Manteiga Balbino","result":"17675","state":"RJ"},{"personId":"2018SELL01","personName":"Carlos Augusto Gianesi Seller","result":"17696","state":"SP"},{"personId":"2019PERE08","personName":"Sávio Alves Cabelo Pereira","result":"17714","state":"SP"},{"personId":"2025ALVE02","personName":"Thales Anício de Souza Alves","result":"17900","state":"MG"},{"personId":"2020BRAN02","personName":"Bernardo Laures Brandão","result":"17908","state":"ES"},{"personId":"2014ABRE01","personName":"Rafael Derrico dos Santos Abreu","result":"17912","state":"SP"},{"personId":"2024ABRA04","personName":"Pedro Alves Abrantes","result":"17919","state":"RJ"},{"personId":"2018OLIV08","personName":"Otávio Gabriel Silva Oliveira","result":"17925","state":"MG"},{"personId":"2016STEA01","personName":"Roberto Steagall","result":"17979","state":"SP"},{"personId":"2015QUIN09","personName":"Valfrido Torres Quintanilha Netto","result":"18047","state":"ES"},{"personId":"2025MACH09","personName":"Daniel Poleszuk Machado","result":"18058","state":"SP"},{"personId":"2023COEL04","personName":"João Pedro Estanek Coelho","result":"18142","state":"RJ"},{"personId":"2009JORG02","personName":"Ronan Felipe Jorge","result":"18221","state":"SP"},{"personId":"2024PERE83","personName":"Leonardo Faria Pereira","result":"18440","state":"SP"},{"personId":"2023STRA33","personName":"Eduardo Ribeiro Strauch","result":"18478","state":"RJ"},{"personId":"2010CARV01","personName":"Gabriel Pitali de Carvalho","result":"18483","state":"SP"},{"personId":"2012TEIX01","personName":"Lucas Medeiros Teixeira","result":"18634","state":"RJ"},{"personId":"2013TEIX02","personName":"Jhonatan Martins Teixeira","result":"18719","state":"SP"},{"personId":"2015MOUL02","personName":"Pedro Moulin","result":"18816","state":"ES"},{"personId":"2018REIS01","personName":"Kaique Valle Verde Reis","result":"18946","state":"MG"},{"personId":"2009SANT04","personName":"Luiz Felipe Parente Santiago","result":"19007","state":"RJ"},{"personId":"2009MOTT01","personName":"Eduardo Lins Motta","result":"19089","state":"RJ"},{"personId":"2011CAMP02","personName":"Rodrigo Guilherme de Campos","result":"19245","state":"SP"},{"personId":"2012CRIC01","personName":"Bruno Galati Paladino Cricelli","result":"19393","state":"SP"},{"personId":"2023CARM10","personName":"Rodrigo Araujo do Carmo","result":"19484","state":"ES"},{"personId":"2009OLIM01","personName":"Gabriel Pavinato Olimpio","result":"19523","state":"SP"},{"personId":"2016CAMP17","personName":"Alécio Henrique Afonso Campos","result":"19540","state":"MG"},{"personId":"2015CAMP17","personName":"Alexandre Henrique Afonso Campos","result":"19668","state":"MG"},{"personId":"2017VICE01","personName":"Marco Tulio Vicentim","result":"19878","state":"SP"},{"personId":"2024CAET01","personName":"Emanuel De Barbi Barcelos Caetano","result":"19897","state":"ES"},{"personId":"2013MORE07","personName":"Victor Moreno","result":"20091","state":"SP"},{"personId":"2015FONS01","personName":"Guilherme Morgado Fonseca","result":"20308","state":"RJ"},{"personId":"2022ANDR34","personName":"Jefferson de Carvalho Andrade","result":"20346","state":"SP"},{"personId":"2007CERP02","personName":"Renan Mondini Cerpe","result":"20678","state":"SP"},{"personId":"2023TEIX02","personName":"Samuel Roveran Esteves Teixeira","result":"20873","state":"SP"},{"personId":"2013MORE02","personName":"Luciane Hissae Tanaka Moreira","result":"20930","state":"SP"},{"personId":"2009ALLE01","personName":"Leandro Vasconcellos Alleoni","result":"20944","state":"SP"},{"personId":"2008FIGU01","personName":"Guilherme Figueira","result":"20995","state":"SP"},{"personId":"2012CAMA01","personName":"Bruno Granato de Araújo Camara","result":"21037","state":"RJ"},{"personId":"2011MESC01","personName":"André Victor Mescollotto","result":"21207","state":"SP"},{"personId":"2024SILV68","personName":"Kauã Soares da Silva","result":"21276","state":"ES"},{"personId":"2017ISSL01","personName":"Beni Issler","result":"21398","state":"SP"},{"personId":"2011SILV05","personName":"Gilson Sousa da Silva","result":"21871","state":"SP"},{"personId":"2015CAMA02","personName":"Brenno Camargo","result":"21995","state":"SP"},{"personId":"2007RIBE01","personName":"Rodrigo Ybarra de Oliveira Ribeiro","result":"22120","state":"SP"},{"personId":"2015MORE15","personName":"Rodrigo Leal Reis Morello","result":"22530","state":"ES"},{"personId":"2007TAMB01","personName":"Leonardo Tambellini","result":"22749","state":"SP"},{"personId":"2010ZELE01","personName":"Felipe Zelenkovas","result":"22753","state":"SP"},{"personId":"2011MIRA01","personName":"Eduardo André Souza de Miranda","result":"24764","state":"SP"},{"personId":"2015CRUZ08","personName":"Guilherme Alves de Campos Cruz","result":"25030","state":"ES"},{"personId":"2015SOAR02","personName":"Gustavo Soares","result":"25211","state":"SP"},{"personId":"2016NUNE16","personName":"Tiago Tiradentes Cuzzuol Nunes","result":"25254","state":"ES"},{"personId":"2013SANT02","personName":"Allan Dênnis Araujo Santos","result":"25778","state":"SP"},{"personId":"2018GUIM02","personName":"Daniel Schreiber Guimarães","result":"25818","state":"RJ"},{"personId":"2008CARA01","personName":"Gilberto Caracciolo Morelli","result":"26396","state":"SP"},{"personId":"2014PAVI02","personName":"Anderson Alessandro Pavia","result":"27766","state":"SP"},{"personId":"2016SANT12","personName":"Andre Luiz Gomes Rangel dos Santos","result":"27804","state":"ES"},{"personId":"2016MASS03","personName":"Davi Nogueira Massariol","result":"27966","state":"ES"},{"personId":"2011FREI01","personName":"Felipe Baldívio Freires","result":"28624","state":"SP"},{"personId":"2007KAWA01","personName":"Marcos Massayuki Kawakami","result":"30854","state":"SP"},{"personId":"2010COLO01","personName":"Bruno Joarlette Coló","result":"30861","state":"SP"},{"personId":"2015SANT37","personName":"Carlos Eduardo da Silva Santos","result":"32739","state":"SP"},{"personId":"2015CAMP04","personName":"Marcela Bertoldi Trujillo Campiteli","result":"35781","state":"SP"},{"personId":"2015VIEI02","personName":"Fabyano Rinaldi Murad Vieira","result":"35921","state":"SP"},{"personId":"2007CERP01","personName":"Alex Mondini Cerpe","result":"36073","state":"SP"},{"personId":"2007BRAU01","personName":"Erica Sumoyama Braune","result":"40933","state":"SP"},{"personId":"2015PERE19","personName":"Adriano Rocha Pereira","result":"50144","state":"SP"},{"personId":"2010FILH01","personName":"Dalcio Rezende Falcão Filho","result":"51001","state":"RJ"}]