[{"personId":"2022PONT02","personName":"Yafah Nicole Aquino Pontes","result":"8879","state":"PI"},{"personId":"2019MACH13","personName":"Wiviane Cassimiro Machado","result":"9978","state":"PI"},{"personId":"2024SILV17","personName":"Kelson Lopes da Silva","result":"10186","state":"PI"},{"personId":"2019SILV56","personName":"Jessé Bezerra da Silva","result":"10196","state":"PI"},{"personId":"2019LIMA12","personName":"Matheus Vinicius da Silva Bastos Lima","result":"10291","state":"PI"},{"personId":"2024AGUI09","personName":"Heitor de Carvalho Aguiar","result":"10370","state":"PI"},{"personId":"2024MOUR03","personName":"João Padua Moura","result":"10922","state":"PI"},{"personId":"2024SANT29","personName":"Davi Sousa Costa Santos","result":"12324","state":"PI"},{"personId":"2024PAIV01","personName":"Samuel Faustino Paiva","result":"12738","state":"PI"},{"personId":"2024ALVE03","personName":"Guilherme de Andrade Alves","result":"12800","state":"PI"},{"personId":"2024BRAN05","personName":"Daniel de Castro Amorim Serpa Brandão","result":"14898","state":"PI"},{"personId":"2024SOUZ04","personName":"Pedro Augusto Passos e Souza","result":"17077","state":"PI"},{"personId":"2014SILV33","personName":"Huérllen Vicente Lemos e Silva","result":"23812","state":"PI"}]