[{"personId":"2014MARQ02","personName":"Marlon de V. Marques","result":"4777","state":"DF"},{"personId":"2019RIBE11","personName":"Bárbara Guerra","result":"7307","state":"DF"},{"personId":"2013MIRA02","personName":"Matheus Barbosa de Miranda","result":"9082","state":"DF"},{"personId":"2024LONG08","personName":"Matheus Carvalho Longo","result":"11105","state":"GO"},{"personId":"2015TAKE03","personName":"Gustavo Kenzo Araki Takechi","result":"15457","state":"DF"},{"personId":"2014SAMP01","personName":"Eduardo Ramalho Sampaio","result":"15702","state":"DF"},{"personId":"2017MART58","personName":"Caio Almeida Martins","result":"16768","state":"GO"},{"personId":"2022SOUS04","personName":"Lucas Dantas de Sousa","result":"17335","state":"DF"},{"personId":"2014MORE05","personName":"Pedro Miranda Moreira","result":"19171","state":"DF"},{"personId":"2024LOYO04","personName":"Marco Aurélio Leão de Loyola","result":"20380","state":"GO"},{"personId":"2022SUZU01","personName":"João Lucas Miranda Suzuki","result":"21065","state":"DF"},{"personId":"2012GIOV02","personName":"Luiggi Giovanucci","result":"22553","state":"GO"},{"personId":"2019SANT84","personName":"Gabriel Dias Souza dos Santos","result":"26157","state":"DF"},{"personId":"2022CAST14","personName":"Arthur Alves Neiva Castro","result":"26512","state":"DF"},{"personId":"2015CHIA03","personName":"Vitor Varjão Chiang","result":"27138","state":"DF"},{"personId":"2023LEIT04","personName":"João Victtor Rocha Leite","result":"27607","state":"GO"},{"personId":"2016BORG04","personName":"Caio Cesar Martins Borges","result":"28564","state":"MT"},{"personId":"2011RAMO03","personName":"Marcel Felipe Aquino Ramos","result":"31078","state":"GO"},{"personId":"2024RODR77","personName":"João Victor Ferro Rodrigues","result":"33839","state":"GO"},{"personId":"2022MART35","personName":"Matheus Oliveira Martins","result":"35174","state":"GO"},{"personId":"2016SANT32","personName":"Matheus Ribeiro dos Santos","result":"39631","state":"GO"},{"personId":"2023CARL18","personName":"Marcelo Augusto Ferreira Carlos","result":"51622","state":"GO"},{"personId":"2011GOME02","personName":"Victor Sinan Seixo de Brito Gomes","result":"52485","state":"GO"},{"personId":"2023MORA71","personName":"Ghabryel Barroso Moraes","result":"55105","state":"MT"},{"personId":"2023FURI02","personName":"Allan Furini","result":"71900","state":"MT"}]