[{"personId":"2019SANT84","personName":"Gabriel Dias Souza dos Santos","result":"12214","state":"DF"},{"personId":"2019RIBE11","personName":"Bárbara Guerra","result":"12516","state":"DF"},{"personId":"2023GODO07","personName":"Miguel Meireles Godoi","result":"14430","state":"DF"},{"personId":"2024LONG08","personName":"Matheus Carvalho Longo","result":"15594","state":"GO"},{"personId":"2012FILH02","personName":"Wagner José de Lima Filho","result":"15668","state":"GO"},{"personId":"2023LEIT04","personName":"João Victtor Rocha Leite","result":"16650","state":"GO"},{"personId":"2016SIMO03","personName":"Lucca Emmanuel Pineli Simões","result":"17042","state":"GO"},{"personId":"2022SUZU01","personName":"João Lucas Miranda Suzuki","result":"17046","state":"DF"},{"personId":"2011ROSA06","personName":"Daniel Waldir Rodrigues Rosa","result":"18167","state":"GO"},{"personId":"2014MORE05","personName":"Pedro Miranda Moreira","result":"19032","state":"DF"},{"personId":"2009KOBA04","personName":"Rodrigo Kenji Asato Kobayashi","result":"19297","state":"MS"},{"personId":"2017MART58","personName":"Caio Almeida Martins","result":"20570","state":"GO"},{"personId":"2023NEIV01","personName":"Felipe Fonseca Gontijo Neiva","result":"20679","state":"GO"},{"personId":"2011GOME02","personName":"Victor Sinan Seixo de Brito Gomes","result":"20851","state":"GO"},{"personId":"2008OLIV01","personName":"Hugo Leonardo de Oliveira Melo","result":"21456","state":"DF"},{"personId":"2012GIOV02","personName":"Luiggi Giovanucci","result":"22129","state":"GO"},{"personId":"2011HENR01","personName":"Roberto Henrique Borges Machado","result":"23722","state":"GO"},{"personId":"2011ALME01","personName":"Diogo Ribeiro de Almeida","result":"25572","state":"GO"},{"personId":"2018SILV72","personName":"Lucas Ferreira Bezerra da Silva","result":"25697","state":"DF"},{"personId":"2024QUEI04","personName":"Roberta Oliveira Garcia Queiroz","result":"27623","state":"DF"},{"personId":"2015PAIX01","personName":"Pablo de Andrade Paixão","result":"27636","state":"MS"},{"personId":"2024MELO02","personName":"Pedro Almeida de Melo","result":"28596","state":"GO"},{"personId":"2022SILV16","personName":"Péricles Oliveira Silva","result":"29811","state":"DF"},{"personId":"2018MORA03","personName":"Paulo Henrique Matos de Moraes","result":"30519","state":"DF"},{"personId":"2011LEAN01","personName":"Renato Freire Leandro","result":"30631","state":"GO"},{"personId":"2014SOUZ05","personName":"José Luiz Martins de Almeida e Souza","result":"31698","state":"DF"},{"personId":"2024THIE05","personName":"Nícolas Zimmermann Thiesen","result":"33228","state":"DF"},{"personId":"2014MARQ02","personName":"Marlon de V. Marques","result":"34386","state":"DF"},{"personId":"2007LAFE01","personName":"Caio José Lafetá","result":"35213","state":"DF"},{"personId":"2022CAST14","personName":"Arthur Alves Neiva Castro","result":"40231","state":"DF"},{"personId":"2009TAMI01","personName":"Gabriel de Souza Tamiozzo","result":"40516","state":"DF"},{"personId":"2024CABA01","personName":"Carolina Ramirez Lopes Cabaleiro","result":"40550","state":"DF"},{"personId":"2024ARAN02","personName":"Luísa Viegas Arantes","result":"43862","state":"DF"},{"personId":"2011CHIC02","personName":"Chen Yu Chi","result":"47600","state":"GO"},{"personId":"2011PERE06","personName":"Eduardo Divino Miranda Pereira","result":"49615","state":"GO"},{"personId":"2017NOVA05","personName":"João Luiz Melo Novaes","result":"52229","state":"DF"}]