[{"id":"6966135","pos":"1","best":"504","average":"544","competitionId":"OpentropolisCEFET2025","roundTypeId":"2","eventId":"333","personId":"2016SATO01","regionalSingleRecord":"NULL","regionalAverageRecord":"SAR","competitionName":"Opentrópolis CEFET 2025","personName":"Caio Hideaki Sato"},{"id":"6333373","pos":"1","best":"462","average":"559","competitionId":"TaboaodaSerraOpen2024","roundTypeId":"f","eventId":"333","personId":"2016SATO01","regionalSingleRecord":"NULL","regionalAverageRecord":"SAR","competitionName":"Taboão da Serra Open 2024","personName":"Caio Hideaki Sato"},{"id":"6280878","pos":"1","best":"473","average":"570","competitionId":"BioFortec2024","roundTypeId":"f","eventId":"333","personId":"2016SATO01","regionalSingleRecord":"NULL","regionalAverageRecord":"SAR","competitionName":"Bio Fortec 2024","personName":"Caio Hideaki Sato"},{"id":"4892624","pos":"1","best":"496","average":"584","competitionId":"ItajaiaoCubo2023","roundTypeId":"1","eventId":"333","personId":"2016SATO01","regionalSingleRecord":"NULL","regionalAverageRecord":"SAR","competitionName":"Itajaí ao Cubo 2023","personName":"Caio Hideaki Sato"},{"id":"4828391","pos":"1","best":"495","average":"590","competitionId":"ColegioAstherOpen2023","roundTypeId":"2","eventId":"333","personId":"2016SATO01","regionalSingleRecord":"NULL","regionalAverageRecord":"SAR","competitionName":"Colégio Asther Open 2023","personName":"Caio Hideaki Sato"},{"id":"4597787","pos":"1","best":"556","average":"624","competitionId":"UNIVROpen2023","roundTypeId":"f","eventId":"333","personId":"2016SATO01","regionalSingleRecord":"NULL","regionalAverageRecord":"SAR","competitionName":"UNIVR Open 2023","personName":"Caio Hideaki Sato"},{"id":"4494410","pos":"1","best":"584","average":"633","competitionId":"FestivalONCUBELindoia2022","roundTypeId":"f","eventId":"333","personId":"2016SATO01","regionalSingleRecord":"NULL","regionalAverageRecord":"SAR","competitionName":"Festival ONCUBE Lindóia 2022","personName":"Caio Hideaki Sato"},{"id":"4468876","pos":"1","best":"580","average":"637","competitionId":"TaipasOpen2022","roundTypeId":"1","eventId":"333","personId":"2016SATO01","regionalSingleRecord":"NULL","regionalAverageRecord":"SAR","competitionName":"Taipas Open 2022","personName":"Caio Hideaki Sato"},{"id":"4385811","pos":"1","best":"518","average":"641","competitionId":"FloripaaoCubo2022","roundTypeId":"2","eventId":"333","personId":"2016SATO01","regionalSingleRecord":"NULL","regionalAverageRecord":"SAR","competitionName":"Floripa ao Cubo 2022","personName":"Caio Hideaki Sato"},{"id":"4124014","pos":"1","best":"613","average":"659","competitionId":"SAC2022","roundTypeId":"3","eventId":"333","personId":"2016SATO01","regionalSingleRecord":"NULL","regionalAverageRecord":"NR","competitionName":"Rubik's WCA South American Championship 2022","personName":"Caio Hideaki Sato"},{"id":"3945913","pos":"1","best":"592","average":"678","competitionId":"OficinaOpen2022","roundTypeId":"1","eventId":"333","personId":"2015CECC01","regionalSingleRecord":"NULL","regionalAverageRecord":"NR","competitionName":"Oficina Open 2022","personName":"Vicenzo Guerino Cecchini"},{"id":"3906492","pos":"1","best":"676","average":"711","competitionId":"FariaBritoOpen2022","roundTypeId":"f","eventId":"333","personId":"2017MAND13","regionalSingleRecord":"NULL","regionalAverageRecord":"NR","competitionName":"Faria Brito Open 2022","personName":"Francisco Moraes Mandalozzo"},{"id":"3869532","pos":"1","best":"670","average":"733","competitionId":"SummerKubeVilaVelha2022","roundTypeId":"1","eventId":"333","personId":"2015CECC01","regionalSingleRecord":"NULL","regionalAverageRecord":"NR","competitionName":"Summer Kube Vila Velha 2022","personName":"Vicenzo Guerino Cecchini"},{"id":"3254171","pos":"1","best":"623","average":"735","competitionId":"VETECJacareiOpen2019","roundTypeId":"f","eventId":"333","personId":"2016SATO01","regionalSingleRecord":"NULL","regionalAverageRecord":"SAR","competitionName":"V ETEC Jacareí Open 2019","personName":"Caio Hideaki Sato"},{"id":"2824551","pos":"1","best":"597","average":"752","competitionId":"CirculoMilitardeCampinas2019","roundTypeId":"f","eventId":"333","personId":"2016SATO01","regionalSingleRecord":"NULL","regionalAverageRecord":"NR","competitionName":"Círculo Militar de Campinas 2019","personName":"Caio Hideaki Sato"},{"id":"2484520","pos":"1","best":"687","average":"773","competitionId":"IIBarueriOpen2018","roundTypeId":"f","eventId":"333","personId":"2016SATO01","regionalSingleRecord":"NULL","regionalAverageRecord":"SAR","competitionName":"II Barueri Open 2018","personName":"Caio Hideaki Sato"},{"id":"2374415","pos":"1","best":"684","average":"780","competitionId":"Brasileiro2018","roundTypeId":"2","eventId":"333","personId":"2016SATO01","regionalSingleRecord":"NULL","regionalAverageRecord":"SAR","competitionName":"Campeonato Brasileiro 2018","personName":"Caio Hideaki Sato"},{"id":"2176669","pos":"1","best":"757","average":"791","competitionId":"ArnoldClassicSouthAmerica2018","roundTypeId":"2","eventId":"333","personId":"2012ROQU01","regionalSingleRecord":"NULL","regionalAverageRecord":"SAR","competitionName":"Arnold Classic South America 2018","personName":"Pedro Roque"},{"id":"909996","pos":"1","best":"758","average":"805","competitionId":"PortoAlegreOpen2015","roundTypeId":"2","eventId":"333","personId":"2012ROQU01","regionalSingleRecord":"NULL","regionalAverageRecord":"SAR","competitionName":"Porto Alegre Open 2015","personName":"Pedro Roque"},{"id":"756371","pos":"1","best":"684","average":"843","competitionId":"BrasiliaOpen2015","roundTypeId":"2","eventId":"333","personId":"2012ROQU01","regionalSingleRecord":"SAR","regionalAverageRecord":"SAR","competitionName":"Brasilia Open 2015","personName":"Pedro Roque"},{"id":"568761","pos":"1","best":"815","average":"880","competitionId":"OficinaOpen2014","roundTypeId":"2","eventId":"333","personId":"2009BARB01","regionalSingleRecord":"NULL","regionalAverageRecord":"SAR","competitionName":"Oficina Open 2014","personName":"Gabriel Dechichi Barbar"},{"id":"473471","pos":"1","best":"800","average":"894","competitionId":"GoianiaOpen2013","roundTypeId":"f","eventId":"333","personId":"2009BARB01","regionalSingleRecord":"NULL","regionalAverageRecord":"SAR","competitionName":"Goiânia Open 2013","personName":"Gabriel Dechichi Barbar"},{"id":"357800","pos":"1","best":"838","average":"923","competitionId":"AmericanaOpen2012","roundTypeId":"2","eventId":"333","personId":"2009BARB01","regionalSingleRecord":"NULL","regionalAverageRecord":"SAR","competitionName":"Americana Open 2012","personName":"Gabriel Dechichi Barbar"},{"id":"330589","pos":"1","best":"890","average":"955","competitionId":"GoianiaOpen2012","roundTypeId":"f","eventId":"333","personId":"2009BARB01","regionalSingleRecord":"NULL","regionalAverageRecord":"SAR","competitionName":"Goiânia Open 2012","personName":"Gabriel Dechichi Barbar"},{"id":"281925","pos":"1","best":"916","average":"957","competitionId":"OficinaOpen2012","roundTypeId":"f","eventId":"333","personId":"2009BARB01","regionalSingleRecord":"NULL","regionalAverageRecord":"SAR","competitionName":"Oficina Open 2012","personName":"Gabriel Dechichi Barbar"},{"id":"281798","pos":"1","best":"859","average":"981","competitionId":"OficinaOpen2012","roundTypeId":"1","eventId":"333","personId":"2009BARB01","regionalSingleRecord":"NULL","regionalAverageRecord":"SAR","competitionName":"Oficina Open 2012","personName":"Gabriel Dechichi Barbar"},{"id":"215364","pos":"1","best":"861","average":"1007","competitionId":"SESCSantos2011","roundTypeId":"2","eventId":"333","personId":"2009BARB01","regionalSingleRecord":"NULL","regionalAverageRecord":"SAR","competitionName":"SESC Santos 2011","personName":"Gabriel Dechichi Barbar"},{"id":"136543","pos":"1","best":"778","average":"1067","competitionId":"SESCSantos2010","roundTypeId":"f","eventId":"333","personId":"2009BARB01","regionalSingleRecord":"SAR","regionalAverageRecord":"SAR","competitionName":"SESC Santos 2010","personName":"Gabriel Dechichi Barbar"},{"id":"136443","pos":"1","best":"1055","average":"1214","competitionId":"SESCSantos2010","roundTypeId":"1","eventId":"333","personId":"2010TERU01","regionalSingleRecord":"NULL","regionalAverageRecord":"SAR","competitionName":"SESC Santos 2010","personName":"Alexandre Key Wakate Teruya"},{"id":"64822","pos":"1","best":"1171","average":"1277","competitionId":"BrasiliaOpen2009","roundTypeId":"2","eventId":"333","personId":"2007GUIM01","regionalSingleRecord":"NULL","regionalAverageRecord":"SAR","competitionName":"Brasília Open 2009","personName":"Pedro Santos Guimarães"},{"id":"44357","pos":"1","best":"1166","average":"1363","competitionId":"SaoPauloOpen2009","roundTypeId":"2","eventId":"333","personId":"2007GUIM01","regionalSingleRecord":"SAR","regionalAverageRecord":"SAR","competitionName":"São Paulo Open 2009","personName":"Pedro Santos Guimarães"},{"id":"31014","pos":"1","best":"1368","average":"1456","competitionId":"MinasOpen2008","roundTypeId":"1","eventId":"333","personId":"2007GUIM01","regionalSingleRecord":"NULL","regionalAverageRecord":"SAR","competitionName":"Minas Open 2008","personName":"Pedro Santos Guimarães"},{"id":"18116","pos":"1","best":"1400","average":"1571","competitionId":"BrazilOpen2007","roundTypeId":"f","eventId":"333","personId":"2007GUIM01","regionalSingleRecord":"NULL","regionalAverageRecord":"SAR","competitionName":"Brazil Open 2007","personName":"Pedro Santos Guimarães"},{"id":"18070","pos":"1","best":"1263","average":"1589","competitionId":"BrazilOpen2007","roundTypeId":"1","eventId":"333","personId":"2007GUIM01","regionalSingleRecord":"SAR","regionalAverageRecord":"SAR","competitionName":"Brazil Open 2007","personName":"Pedro Santos Guimarães"},{"id":"15354","pos":"33","best":"1577","average":"1667","competitionId":"WC2007","roundTypeId":"1","eventId":"333","personId":"2007GUIM01","regionalSingleRecord":"SAR","regionalAverageRecord":"SAR","competitionName":"World Rubik's Cube Championship 2007","personName":"Pedro Santos Guimarães"}]