[{"id":"5236900","pos":"1","best":"43572","average":"48422","competitionId":"SilentBrasilia2023","roundTypeId":"f","eventId":"555bf","personId":"2017SEMO02","regionalSingleRecord":"NULL","regionalAverageRecord":"NR","competitionName":"Silent Brasília 2023","personName":"Marcos Ferreira Semolini"},{"id":"3639622","pos":"2","best":"95800","average":"98500","competitionId":"TcheAquieta2020","roundTypeId":"f","eventId":"555bf","personId":"2017SEMO02","regionalSingleRecord":"NULL","regionalAverageRecord":"SAR","competitionName":"Tchê Aquieta 2020","personName":"Marcos Ferreira Semolini"}]