[{"personId":"2012ROQU01","personName":"Pedro Roque","result":"2549","state":"MG"},{"personId":"2015CAMP01","personName":"Rafael Carreiro Campos","result":"3066","state":"MG"},{"personId":"2009BARB01","personName":"Gabriel Dechichi Barbar","result":"3206","state":"MG"},{"personId":"2017SOUZ10","personName":"Gabriel Lincon Souza","result":"3241","state":"MG"},{"personId":"2015FIGU02","personName":"Marcus Figueiredo","result":"3288","state":"MG"},{"personId":"2024SANT15","personName":"Mariane Martins dos Santos","result":"3381","state":"MG"},{"personId":"2017REZE01","personName":"Vitória Santana Rezende","result":"3500","state":"MG"},{"personId":"2017MEDE01","personName":"Ricardo Magno Santos Medeiros","result":"3620","state":"MG"},{"personId":"2014REZE02","personName":"Matheus de Souza Rezende","result":"3727","state":"MG"},{"personId":"2017NANT01","personName":"Erik Lucas Santos Nantes","result":"3778","state":"MG"},{"personId":"2024FELI11","personName":"Gabriel Pereira Felipe","result":"3823","state":"MG"},{"personId":"2024RIOS12","personName":"Gabriel Assis Rios","result":"3865","state":"MG"},{"personId":"2015SILV62","personName":"Pedro Victor Ferreira Silva","result":"4086","state":"MG"},{"personId":"2018CARR06","personName":"Leonardo José Carrari","result":"4208","state":"MG"},{"personId":"2024MIZU03","personName":"Diego Eiji Akatsuka Mizuta","result":"4367","state":"MG"},{"personId":"2022MACH17","personName":"Miguel Wohnrath Machado","result":"4385","state":"MG"},{"personId":"2022PERE49","personName":"Gustavo Gonçalves Pereira","result":"4421","state":"MG"},{"personId":"2007GUIM01","personName":"Pedro Santos Guimarães","result":"4606","state":"MG"},{"personId":"2024VASS01","personName":"Daniel Arruda Vasseur","result":"4666","state":"MG"},{"personId":"2022NADE05","personName":"Paulo Korowajczuk Nader","result":"4830","state":"MG"},{"personId":"2022SANT52","personName":"Carlos Lumumba Soares dos Santos","result":"4942","state":"MG"},{"personId":"2019BRET01","personName":"Lucas Jagger Vieira Laca Bretas","result":"5219","state":"MG"},{"personId":"2018COST11","personName":"Maurício Amaral da Costa","result":"5484","state":"MG"},{"personId":"2024MORA61","personName":"André Fazito Morais","result":"5635","state":"MG"},{"personId":"2018SILV47","personName":"Gabriel Pedra Silveira","result":"5664","state":"MG"},{"personId":"2025ALVE02","personName":"Thales Anício de Souza Alves","result":"5791","state":"MG"},{"personId":"2017VIEI04","personName":"Samuel Castro Vieira","result":"6042","state":"MG"},{"personId":"2017PERE58","personName":"Vitor Samuel Pereira","result":"6105","state":"MG"},{"personId":"2019VIEI03","personName":"Eduardo de Carvalho Vieira","result":"6398","state":"MG"},{"personId":"2018RODR59","personName":"André Felipe Silva Rodrigues","result":"6534","state":"MG"},{"personId":"2018SILV34","personName":"Jean Carlo Gonçalves Satiro da Silva","result":"6607","state":"MG"},{"personId":"2016BART08","personName":"Gabriel Henrique Cabral Barthasson","result":"6665","state":"MG"},{"personId":"2022MAFO01","personName":"João Pedro Guedes Mafort","result":"6794","state":"MG"},{"personId":"2018OLIV08","personName":"Otávio Gabriel Silva Oliveira","result":"6813","state":"MG"},{"personId":"2024RIBE02","personName":"Bianca de Souza Pinto Ribeiro","result":"6833","state":"MG"},{"personId":"2015MESQ01","personName":"Paulo Victor Mourais Mesquita","result":"6911","state":"MG"},{"personId":"2025SANT34","personName":"Samir Oliveira Ramos dos Santos","result":"6945","state":"MG"},{"personId":"2015CAMP17","personName":"Alexandre Henrique Afonso Campos","result":"7056","state":"MG"},{"personId":"2017CAMA16","personName":"André Silva Camargo","result":"7163","state":"MG"},{"personId":"2025MURT02","personName":"Guilherme Rocha Murta","result":"7811","state":"MG"},{"personId":"2017WEST04","personName":"Nicolas Perez","result":"7892","state":"MG"},{"personId":"2018REIS01","personName":"Kaique Valle Verde Reis","result":"7996","state":"MG"},{"personId":"2025SILV16","personName":"João Borba Alvares da Silva","result":"8037","state":"MG"},{"personId":"2017COST06","personName":"Lara P. Velho Costa","result":"8080","state":"MG"},{"personId":"2024CONT20","personName":"Miguel Agero De Conti","result":"8152","state":"MG"},{"personId":"2017CASA05","personName":"João Francisco Stolle Paixão e Casarões","result":"8326","state":"MG"},{"personId":"2024JESU08","personName":"Willian Eustaquio dos Santos Jesus","result":"8360","state":"MG"},{"personId":"2016GOME21","personName":"Henrique Boaventura de Lima Gomes","result":"8628","state":"MG"},{"personId":"2015SAPE01","personName":"Pedro Henrique Santos Arruda de Sá","result":"8811","state":"MG"},{"personId":"2017JUNH03","personName":"João Pedro Ribeiro Junho","result":"9166","state":"MG"},{"personId":"2017GOME28","personName":"Guilherme Serra Camargo Gomes","result":"9263","state":"MG"},{"personId":"2016CAMP17","personName":"Alécio Henrique Afonso Campos","result":"9298","state":"MG"},{"personId":"2017SANT65","personName":"Alexandre Nascimento dos Santos","result":"9747","state":"MG"},{"personId":"2019PAUL03","personName":"Hélio Abrahão de Paula","result":"10029","state":"MG"},{"personId":"2019FRAN07","personName":"Lucas Franklin Batista França","result":"10305","state":"MG"},{"personId":"2019JUNI03","personName":"Ernando Junior","result":"10533","state":"MG"},{"personId":"2017ROMA08","personName":"Bernardo Brum de Paiva Romano","result":"10647","state":"MG"},{"personId":"2017LOUR03","personName":"Maycon Felipe Lourenço","result":"11046","state":"MG"},{"personId":"2023ROCH11","personName":"João Victor Machado Rocha","result":"11200","state":"MG"},{"personId":"2018GUAR03","personName":"Thiago Balsamão Guarda","result":"11364","state":"MG"},{"personId":"2025MILA02","personName":"Lucas Agostinho Milagre","result":"11375","state":"MG"},{"personId":"2015COST10","personName":"Ramon Griffo Costa","result":"11525","state":"MG"},{"personId":"2019PERE05","personName":"Igor Santos Pereira","result":"11531","state":"MG"},{"personId":"2015KANO01","personName":"Arthur Alex Akihiro Kano","result":"12067","state":"MG"},{"personId":"2018DIAS03","personName":"Pedro Paulo Dias","result":"12121","state":"MG"},{"personId":"2024FANT02","personName":"Eduardo de Almeida Fantauzzi","result":"12240","state":"MG"},{"personId":"2025STOC01","personName":"Sarah Felix Stocler","result":"12275","state":"MG"},{"personId":"2017PAUL12","personName":"João Vítor Aredes Martins Paulo","result":"12453","state":"MG"},{"personId":"2024MASC03","personName":"Tiago da Mata Mascarenhas","result":"12552","state":"MG"},{"personId":"2017RIBE05","personName":"João Vítor Silva Ribeiro","result":"12759","state":"MG"},{"personId":"2025SILV61","personName":"Heloisa Laura Silva","result":"13021","state":"MG"},{"personId":"2019NASC05","personName":"Pedro Rodrigues Pinho Nascimento","result":"13056","state":"MG"},{"personId":"2018PERE34","personName":"Guilherme de Sousa Pereira","result":"13452","state":"MG"},{"personId":"2017BREN03","personName":"David Breno","result":"13755","state":"MG"},{"personId":"2023MANZ05","personName":"Rafael Duarte Manzan","result":"13763","state":"MG"},{"personId":"2024MAZO02","personName":"Samuel Gontijo Mazoni","result":"14874","state":"MG"},{"personId":"2015CORR04","personName":"Pedro Henrique Oliveira Corrêa","result":"15007","state":"MG"},{"personId":"2018BATI01","personName":"Ana Luisa do Amaral Batista","result":"16242","state":"MG"},{"personId":"2007BRIT01","personName":"Michael Avelino Britto","result":"17029","state":"MG"},{"personId":"2017GONT02","personName":"Romão Aldany Silva Gontijo","result":"17578","state":"MG"},{"personId":"2018SILV35","personName":"Franklyn Xavier Silverio","result":"18394","state":"MG"},{"personId":"2017GOME27","personName":"André Júnio de Vasconcelos Gomes","result":"18753","state":"MG"},{"personId":"2016BARR19","personName":"Erick Alcantara Barrem","result":"19187","state":"MG"}]