[{"personId":"2015RIBE06","personName":"Maciel Bruno da Silva Ribeiro","result":"11933","state":"MA"},{"personId":"2014FERR01","personName":"Davi Silva Soares Ferreira","result":"14834","state":"MA"},{"personId":"2017SILV44","personName":"Italo Mateus Cardoso Da Silva","result":"18790","state":"MA"},{"personId":"2014VITO01","personName":"Francisco Lucas Sousa Vitório","result":"24404","state":"MA"},{"personId":"2016NETO07","personName":"Carlos Alberto Santos Maranhão Neto","result":"28724","state":"MA"},{"personId":"2013VIEI02","personName":"Gabriel Cantanhêde Vieira","result":"39220","state":"MA"}]