[{"personId":"2019MENE04","personName":"Lucas Cordeiro do Vale Menezes","result":"25","state":"CE"},{"personId":"2013BRIT01","personName":"Gustavo Penaforte Brito","result":"30","state":"CE"},{"personId":"2013SOUS03","personName":"Francisco Thales Rocha Sousa","result":"32","state":"CE"},{"personId":"2019RODR38","personName":"Thiago de Oliveira Rodrigues","result":"36","state":"CE"},{"personId":"2024SOUS07","personName":"Gabriel Nascimento Sousa","result":"36","state":"CE"},{"personId":"2024NASC01","personName":"Mikael Ribeiro do Nascimento","result":"44","state":"CE"},{"personId":"2019MENE03","personName":"Levi Cordeiro do Vale Menezes","result":"49","state":"CE"}]